civilianM/__init__.py
civilianM/cert.py
civilianM/login.py
civilianM/math.py
civilianM/memory.py
civilianM/t.py
civilianM/tiger.py
civilianM-2.8.97.dist-info/LICENSE
civilianM-2.8.97.dist-info/METADATA
civilianM-2.8.97.dist-info/WHEEL
civilianM-2.8.97.dist-info/top_level.txt
civilianM-2.8.97.dist-info/RECORD
