Metadata-Version: 2.1
Name: civilianM
Version: 2.8.97
Summary: Common functions,More will be added in the future,Look forward to your use
Home-page: UNKNOWN
Author: AC97
Author-email: ehcemc@hotmail.com
License: UNKNOWN
Platform: UNKNOWN
Classifier: Programming Language :: Python :: 3
Classifier: License :: OSI Approved :: MIT License
Classifier: Operating System :: OS Independent
Requires: BeautifulSoup4
Requires: requests
Requires: lxml
License-File: LICENSE
Requires-Dist: BeautifulSoup4
Requires-Dist: requests
Requires-Dist: lxml
